autospice-0.2.0.dist-info/licenses/LICENSE
spice/__init__.py
spice/estimator.py
spice/pipeline_rnn.py
spice/pipeline_sindy.py
spice/precoded.py
spice/resources/__init__.py
spice/resources/bandits.py
spice/resources/fit_sindy.py
spice/resources/model_evaluation.py
spice/resources/optimizer_selection.py
spice/resources/rnn.py
spice/resources/rnn_training.py
spice/resources/rnn_utils.py
spice/resources/sindy_training.py
spice/resources/sindy_utils.py
spice/utils/__init__.py
spice/utils/convert_dataset.py
spice/utils/plotting.py
spice/utils/setup_agents.py
autospice-0.2.0.dist-info/METADATA
autospice-0.2.0.dist-info/WHEEL
autospice-0.2.0.dist-info/top_level.txt
autospice-0.2.0.dist-info/RECORD
