Metadata-Version: 2.4
Name: autospice
Version: 0.2.0
Summary: SPICE: Sparse and Interpretable Cognitive Equations
Author-email: Daniel Weinhardt <daniel.weinhardt@uni-osnabrueck.de>
Maintainer-email: Muhip Tezcan <itezcan@uni-osnabrueck.de>
License: MIT License
Project-URL: Issues, https://github.com/whyhardt/SPICE/issues
Project-URL: Repository, https://github.com/whyhardt/SPICE
Project-URL: Documentation, https://whyhardt.github.io/SPICE/
Keywords: cognitive-science,reinforcement-learning,machine-learning,rnn,dynamical-systems,sindy
Classifier: Development Status :: 3 - Alpha
Classifier: Intended Audience :: Science/Research
Classifier: License :: OSI Approved :: MIT License
Classifier: Operating System :: OS Independent
Classifier: Programming Language :: Python :: 3
Classifier: Programming Language :: Python :: 3.11
Classifier: Topic :: Scientific/Engineering :: Artificial Intelligence
Requires-Python: >=3.11
License-File: LICENSE
Requires-Dist: arviz<0.21.0,>=0.20.0
Requires-Dist: jax<0.5.0,>=0.4.35
Requires-Dist: matplotlib<4.0.0,>=3.10.0
Requires-Dist: numpy<2.0.0,>=1.21.0
Requires-Dist: numpyro<0.16.0,>=0.15.0
Requires-Dist: pandas<3.0.0,>=2.2.0
Requires-Dist: pymc<6.0.0,>=5.21.0
Requires-Dist: pyro_ppl<2.0.0,>=1.9.0
Requires-Dist: pysindy<2.0.0,>=1.7.0
Requires-Dist: scikit-learn<2.0.0,>=1.0.0
Requires-Dist: scipy<2.0.0,>=1.15.0
Requires-Dist: seaborn<0.14.0,>=0.13.0
Requires-Dist: torch<3.0.0,>=2.0.0
Requires-Dist: tqdm>=4.65.0
Requires-Dist: optuna<5.0.0,>=4.3.0
Requires-Dist: dill<0.5.0,>=0.4.0
Requires-Dist: pytest>=7.0.0
Provides-Extra: dev
Requires-Dist: pytest>=7.0.0; extra == "dev"
Dynamic: license-file
